odoo/addons/purchase_packaging_default/README.rst
odoo/addons/purchase_packaging_default/__init__.py
odoo/addons/purchase_packaging_default/__manifest__.py
odoo/addons/purchase_packaging_default/i18n/it.po
odoo/addons/purchase_packaging_default/i18n/purchase_packaging_default.pot
odoo/addons/purchase_packaging_default/models/__init__.py
odoo/addons/purchase_packaging_default/models/product_packaging.py
odoo/addons/purchase_packaging_default/models/purchase_order_line.py
odoo/addons/purchase_packaging_default/models/res_company.py
odoo/addons/purchase_packaging_default/models/res_config_settings.py
odoo/addons/purchase_packaging_default/readme/CONTRIBUTORS.rst
odoo/addons/purchase_packaging_default/readme/DESCRIPTION.rst
odoo/addons/purchase_packaging_default/static/description/icon.png
odoo/addons/purchase_packaging_default/static/description/index.html
odoo/addons/purchase_packaging_default/tests/__init__.py
odoo/addons/purchase_packaging_default/tests/test_purchase_packaging_default.py
odoo/addons/purchase_packaging_default/views/res_config_settings_views.xml
odoo_addon_purchase_packaging_default-16.0.1.1.0.dist-info/METADATA
odoo_addon_purchase_packaging_default-16.0.1.1.0.dist-info/WHEEL
odoo_addon_purchase_packaging_default-16.0.1.1.0.dist-info/top_level.txt
odoo_addon_purchase_packaging_default-16.0.1.1.0.dist-info/RECORD
